stringdb_alias/__init__.py
stringdb_alias/mapper.py
stringdb_alias-1.0.dist-info/LICENSE
stringdb_alias-1.0.dist-info/METADATA
stringdb_alias-1.0.dist-info/WHEEL
stringdb_alias-1.0.dist-info/top_level.txt
stringdb_alias-1.0.dist-info/RECORD
